event_schemas/__init__.py
event_schemas/apps/__init__.py
event_schemas/apps/advisor/__init__.py
event_schemas/apps/advisor/v1/__init__.py
event_schemas/apps/advisor/v1/advisor_recommendations.py
event_schemas/apps/export_service/__init__.py
event_schemas/apps/export_service/v1/__init__.py
event_schemas/apps/export_service/v1/resource_request.py
event_schemas/apps/policies/__init__.py
event_schemas/apps/policies/v1/__init__.py
event_schemas/apps/policies/v1/policy_triggered.py
event_schemas/apps/repositories/__init__.py
event_schemas/apps/repositories/v1/__init__.py
event_schemas/apps/repositories/v1/repository_events.py
event_schemas/core/__init__.py
event_schemas/core/v1/__init__.py
event_schemas/core/v1/error.py
event_schemas/core/v1/notification.py
event_schemas/core/v1/rhel_system.py
crc_event_schemas-0.1.7.dist-info/LICENSE.txt
crc_event_schemas-0.1.7.dist-info/METADATA
crc_event_schemas-0.1.7.dist-info/WHEEL
crc_event_schemas-0.1.7.dist-info/top_level.txt
crc_event_schemas-0.1.7.dist-info/RECORD
