Metadata-Version: 2.1
Name: crc-event-schemas
Version: 0.1.7
Summary: CloudEvents type bindings for console.redhat.com
Home-page: https://github.com/RedHatInsights/event-schemas-python
License-File: LICENSE.txt
